{
  "gitSyncId": "690080acd1a018060dd5eb42_265b15e7-3f87-49b4-bd45-050eed1a1eb5",
  "id": "Edit Order or Quote_utils.formatLineItems",
  "pluginId": "js-plugin",
  "pluginType": "JS",
  "unpublishedAction": {
    "actionConfiguration": {
      "encodeParamsToggle": true,
      "jsArguments": [],
      "paginationType": "NONE",
      "timeoutInMillisecond": 10000
    },
    "collectionId": "Edit Order or Quote_utils",
    "confirmBeforeExecute": false,
    "datasource": {
      "isAutoGenerated": false,
      "name": "UNUSED_DATASOURCE",
      "pluginId": "js-plugin"
    },
    "dynamicBindingPathList": [
      {
        "key": "body"
      }
    ],
    "fullyQualifiedName": "utils.formatLineItems",
    "name": "formatLineItems",
    "pageId": "Edit Order or Quote",
    "runBehaviour": "MANUAL",
    "userSetOnLoad": false
  }
}