{
  "accentColor": "{{appsmith.theme.colors.primaryColor}}",
  "additionalStaticProps": [
    "level",
    "levelData",
    "prefixMetaWidgetId",
    "metaWidgetId"
  ],
  "animateLoading": true,
  "backgroundColor": "#93c5fd",
  "borderRadius": "{{appsmith.theme.borderRadius.appBorderRadius}}",
  "bottomRow": 69,
  "boxShadow": "{{appsmith.theme.boxShadow.appBoxShadow}}",
  "children": [
    {
      "borderRadius": "{{appsmith.theme.borderRadius.appBorderRadius}}",
      "bottomRow": 650,
      "boxShadow": "{{appsmith.theme.boxShadow.appBoxShadow}}",
      "canExtend": false,
      "containerStyle": "none",
      "detachFromLayout": true,
      "dropDisabled": true,
      "dynamicBindingPathList": [
        {
          "key": "borderRadius"
        },
        {
          "key": "boxShadow"
        }
      ],
      "dynamicHeight": "AUTO_HEIGHT",
      "flexLayers": [],
      "isLoading": false,
      "isVisible": true,
      "key": "g3pi3xnbmq",
      "leftColumn": 0,
      "maxDynamicHeight": 9000,
      "minDynamicHeight": 4,
      "minHeight": 400,
      "minWidth": 450,
      "mobileBottomRow": 400,
      "mobileLeftColumn": 0,
      "mobileRightColumn": 599.9296875,
      "mobileTopRow": 0,
      "needsErrorInfo": false,
      "noPad": true,
      "openParentPropertyPane": true,
      "parentColumnSpace": 1,
      "parentId": "wubm8j9j2e",
      "parentRowSpace": 1,
      "renderMode": "CANVAS",
      "responsiveBehavior": "fill",
      "rightColumn": 599.9296875,
      "topRow": 0,
      "type": "CANVAS_WIDGET",
      "version": 1,
      "widgetId": "jdsalgbjf1",
      "widgetName": "Canvas9Copy"
    }
  ],
  "currentItemsView": "{{[]}}",
  "dynamicBindingPathList": [
    {
      "key": "currentItemsView"
    },
    {
      "key": "selectedItemView"
    },
    {
      "key": "triggeredItemView"
    },
    {
      "key": "primaryKeys"
    },
    {
      "key": "accentColor"
    },
    {
      "key": "borderRadius"
    },
    {
      "key": "boxShadow"
    },
    {
      "key": "listData"
    }
  ],
  "dynamicTriggerPathList": [
    {
      "key": "onPageChange"
    }
  ],
  "enhancements": true,
  "flexVerticalAlignment": "start",
  "gridType": "vertical",
  "hasMetaWidgets": true,
  "isCanvas": true,
  "isLoading": false,
  "isVisible": true,
  "itemBackgroundColor": "#FFFFFF",
  "itemSpacing": 8,
  "key": "l2cb0ru3vh",
  "leftColumn": 49,
  "listData": "{{appsmith.store.imagesArray}}",
  "mainCanvasId": "jdsalgbjf1",
  "mainContainerId": "ulxawflkxo",
  "minWidth": 450,
  "mobileBottomRow": 44,
  "mobileLeftColumn": 0,
  "mobileRightColumn": 24,
  "mobileTopRow": 4,
  "needsErrorInfo": false,
  "onPageChange": "{{Media_get_images.run({\n \"page\": List1.pageNo,\n});}}",
  "pageSize": 5,
  "parentColumnSpace": 24.9970703125,
  "parentId": "g3o6lu2qx5",
  "parentRowSpace": 10,
  "primaryKeys": "{{List1Copy.listData.map((currentItem, currentIndex) => currentItem[\"id\"] )}}",
  "renderMode": "CANVAS",
  "requiresFlatWidgetChildren": true,
  "responsiveBehavior": "fill",
  "rightColumn": 63,
  "selectedItemView": "{{{}}}",
  "serverSidePagination": false,
  "templateHeight": 160,
  "topRow": 4,
  "totalRecordsCount": "",
  "triggeredItemView": "{{{}}}",
  "type": "LIST_WIDGET_V2",
  "widgetId": "wubm8j9j2e",
  "widgetName": "List1Copy"
}