{
  "accentColor": "{{appsmith.theme.colors.primaryColor}}",
  "additionalStaticProps": [
    "level",
    "levelData",
    "prefixMetaWidgetId",
    "metaWidgetId"
  ],
  "animateLoading": true,
  "backgroundColor": "transparent",
  "borderRadius": "{{appsmith.theme.borderRadius.appBorderRadius}}",
  "bottomRow": 137,
  "boxShadow": "{{appsmith.theme.boxShadow.appBoxShadow}}",
  "children": [
    {
      "borderRadius": "{{appsmith.theme.borderRadius.appBorderRadius}}",
      "bottomRow": 650,
      "boxShadow": "{{appsmith.theme.boxShadow.appBoxShadow}}",
      "canExtend": false,
      "containerStyle": "none",
      "detachFromLayout": true,
      "dropDisabled": true,
      "dynamicBindingPathList": [
        {
          "key": "borderRadius"
        },
        {
          "key": "boxShadow"
        }
      ],
      "dynamicHeight": "AUTO_HEIGHT",
      "flexLayers": [],
      "isLoading": false,
      "isVisible": true,
      "key": "1zqx4fd3fn",
      "leftColumn": 0,
      "maxDynamicHeight": 9000,
      "minDynamicHeight": 4,
      "minHeight": 400,
      "minWidth": 450,
      "mobileBottomRow": 400,
      "mobileLeftColumn": 0,
      "mobileRightColumn": 726,
      "mobileTopRow": 0,
      "needsErrorInfo": false,
      "noPad": true,
      "openParentPropertyPane": true,
      "parentColumnSpace": 1,
      "parentId": "gwlqcyb4vj",
      "parentRowSpace": 1,
      "renderMode": "CANVAS",
      "responsiveBehavior": "fill",
      "rightColumn": 726,
      "topRow": 0,
      "type": "CANVAS_WIDGET",
      "version": 1,
      "widgetId": "t7n84rsftj",
      "widgetName": "Canvas6"
    }
  ],
  "currentItemsView": "{{[]}}",
  "dynamicBindingPathList": [
    {
      "key": "currentItemsView"
    },
    {
      "key": "selectedItemView"
    },
    {
      "key": "triggeredItemView"
    },
    {
      "key": "primaryKeys"
    },
    {
      "key": "accentColor"
    },
    {
      "key": "borderRadius"
    },
    {
      "key": "boxShadow"
    },
    {
      "key": "listData"
    }
  ],
  "dynamicTriggerPathList": [],
  "enhancements": true,
  "flexVerticalAlignment": "start",
  "gridType": "vertical",
  "hasMetaWidgets": true,
  "isCanvas": true,
  "isLoading": false,
  "isVisible": true,
  "itemBackgroundColor": "#FFFFFF",
  "itemSpacing": 8,
  "key": "51yb4a9lr2",
  "leftColumn": 0,
  "listData": "{{data.retrieveAnOrderLineItems.data}}",
  "mainCanvasId": "t7n84rsftj",
  "mainContainerId": "0o08d7oymm",
  "minWidth": 450,
  "mobileBottomRow": 118,
  "mobileLeftColumn": 10,
  "mobileRightColumn": 34,
  "mobileTopRow": 78,
  "needsErrorInfo": false,
  "originalBottomRow": 137,
  "originalTopRow": 72,
  "pageSize": 4,
  "parentColumnSpace": 30.25,
  "parentId": "op43a4znbo",
  "parentRowSpace": 10,
  "primaryKeys": "{{List1.listData.map((currentItem, currentIndex) => currentItem[\"id\"] )}}",
  "renderMode": "CANVAS",
  "requiresFlatWidgetChildren": true,
  "responsiveBehavior": "fill",
  "rightColumn": 64,
  "selectedItemView": "{{{}}}",
  "templateHeight": 160,
  "topRow": 72,
  "triggeredItemView": "{{{}}}",
  "type": "LIST_WIDGET_V2",
  "widgetId": "gwlqcyb4vj",
  "widgetName": "List1"
}