{
  "gitSyncId": "690080acd1a018060dd5eb42_68926f71-6acd-4c3c-944d-a8ae5a3cc37d",
  "id": "Add New Products_utils.removeImage",
  "pluginId": "js-plugin",
  "pluginType": "JS",
  "unpublishedAction": {
    "actionConfiguration": {
      "encodeParamsToggle": true,
      "jsArguments": [
        {
          "name": "idToRemove"
        }
      ],
      "paginationType": "NONE",
      "timeoutInMillisecond": 10000
    },
    "collectionId": "Add New Products_utils",
    "confirmBeforeExecute": false,
    "datasource": {
      "isAutoGenerated": false,
      "name": "UNUSED_DATASOURCE",
      "pluginId": "js-plugin"
    },
    "dynamicBindingPathList": [
      {
        "key": "body"
      }
    ],
    "fullyQualifiedName": "utils.removeImage",
    "name": "removeImage",
    "pageId": "Add New Products",
    "runBehaviour": "MANUAL",
    "userSetOnLoad": false
  }
}