{
  "animateLoading": true,
  "bottomRow": 12,
  "capSide": 0,
  "capType": "nc",
  "dividerColor": "#858282",
  "dynamicBindingPathList": [],
  "dynamicTriggerPathList": [],
  "isLoading": false,
  "isVisible": true,
  "key": "p1xlrkd1pe",
  "leftColumn": 20,
  "minWidth": 450,
  "mobileBottomRow": 15,
  "mobileLeftColumn": 29,
  "mobileRightColumn": 49,
  "mobileTopRow": 11,
  "needsErrorInfo": false,
  "orientation": "vertical",
  "originalBottomRow": 12,
  "originalTopRow": 5,
  "parentColumnSpace": 30.25,
  "parentId": "x5unbdj4d5",
  "parentRowSpace": 10,
  "renderMode": "CANVAS",
  "responsiveBehavior": "fill",
  "rightColumn": 22,
  "strokeStyle": "solid",
  "thickness": 2,
  "topRow": 5,
  "type": "DIVIDER_WIDGET",
  "version": 1,
  "widgetId": "36q361pu9v",
  "widgetName": "Divider1"
}