{
  "gitSyncId": "68c1972c92810156b121ec4e_71d2bf1e-11eb-4511-8751-fafad3885893",
  "id": "BER Assets_JSObject1.myFun2",
  "pluginId": "js-plugin",
  "pluginType": "JS",
  "unpublishedAction": {
    "actionConfiguration": {
      "encodeParamsToggle": true,
      "jsArguments": [],
      "paginationType": "NONE",
      "timeoutInMillisecond": 10000
    },
    "clientSideExecution": true,
    "collectionId": "BER Assets_JSObject1",
    "confirmBeforeExecute": false,
    "datasource": {
      "isAutoGenerated": false,
      "name": "UNUSED_DATASOURCE",
      "pluginId": "js-plugin"
    },
    "dynamicBindingPathList": [
      {
        "key": "body"
      }
    ],
    "fullyQualifiedName": "JSObject1.myFun2",
    "name": "myFun2",
    "pageId": "BER Assets",
    "runBehaviour": "MANUAL",
    "userSetOnLoad": false
  }
}