{
  "animateLoading": true,
  "borderRadius": "{{appsmith.theme.borderRadius.appBorderRadius}}",
  "bottomRow": 22,
  "boxShadow": "{{utils.statusSetting.data === \"all\"? '0 10px 15px -3px rgba(0, 0, 0, 0.1), 0 4px 6px -2px rgba(0, 0, 0, 0.05)' : 'none'}}",
  "buttonColor": "{{utils.statusTypes('no-status').primaryColor}}",
  "buttonVariant": "{{utils.statusSetting.data === \"all\"? \"PRIMARY\" : \"SECONDARY\"}}",
  "disabledWhenInvalid": false,
  "dynamicBindingPathList": [
    {
      "key": "borderRadius"
    },
    {
      "key": "buttonVariant"
    },
    {
      "key": "boxShadow"
    },
    {
      "key": "buttonColor"
    }
  ],
  "dynamicPropertyPathList": [
    {
      "key": "buttonVariant"
    },
    {
      "key": "boxShadow"
    },
    {
      "key": "buttonColor"
    }
  ],
  "dynamicTriggerPathList": [
    {
      "key": "onClick"
    }
  ],
  "isDefaultClickDisabled": true,
  "isDisabled": false,
  "isLoading": false,
  "isVisible": true,
  "key": "65yuuxfgm3",
  "leftColumn": 21,
  "minWidth": 120,
  "mobileBottomRow": 15,
  "mobileLeftColumn": 27,
  "mobileRightColumn": 43,
  "mobileTopRow": 11,
  "needsErrorInfo": false,
  "onClick": "{{utils.statusSetting('all');}}",
  "parentColumnSpace": 30.5625,
  "parentId": "0",
  "parentRowSpace": 10,
  "placement": "CENTER",
  "recaptchaType": "V3",
  "renderMode": "CANVAS",
  "resetFormOnClick": false,
  "responsiveBehavior": "hug",
  "rightColumn": 27,
  "text": "All",
  "topRow": 18,
  "type": "BUTTON_WIDGET",
  "version": 1,
  "widgetId": "60iv9l6p46",
  "widgetName": "Button1"
}